README.rst
setup.py
kite_mail/__init__.py
kite_mail/cli.py
kite_mail/mail.py
kite_mail/utils.py
kite_mail.egg-info/PKG-INFO
kite_mail.egg-info/SOURCES.txt
kite_mail.egg-info/dependency_links.txt
kite_mail.egg-info/entry_points.txt
kite_mail.egg-info/pbr.json
kite_mail.egg-info/requires.txt
kite_mail.egg-info/top_level.txt