Metadata-Version: 1.1
Name: kite-mail
Version: 0.0.0.dev0
Summary: kite-mail is a command-line tool to request the contents of e-mail to takosan .
Home-page: UNKNOWN
Author: Kei Iwasaki
Author-email: me@laughk.org
License: MIT License
Platform: UNKNOWN
Classifier: License :: OSI Approved :: MIT License
Classifier: Programming Language :: Python :: 2.6
Classifier: Programming Language :: Python :: 2.7
Classifier: Programming Language :: Python :: 3
